{
  "settings": {
    "fps": 44.600,
    "filter": "NO FILTERS"
  },
  "scene": {
    "camera": {
      "position": [1.088, 45.293, -155.872],
      "direction": [-0.999, 0.005, 0.043],
      "rotation": 12.544
    },
    "lights": [
      {
        "name": "Unnamed_0",
        "type": "AMBIENT",
        "intensity": 0.075
      },
      {
        "name": "Unnamed_1",
        "type": "POINT",
        "intensity": 0.500,
        "position": [-4.000, 5.000, -13.000]
      },
      {
        "name": "Unnamed_2",
        "type": "DIRECTION",
        "intensity": 0.300,
        "direction": [0.424, -0.566, 0.707]
      },
      {
        "name": "Light",
        "type": "POINT",
        "intensity": 0.300,
        "position": [-1.836, 50.190, -154.660]
      },
      {
        "name": "Light",
        "type": "POINT",
        "intensity": 0.300,
        "position": [-8.830, 50.227, -154.360]
      },
      {
        "name": "Light",
        "type": "POINT",
        "intensity": 0.300,
        "position": [-6.832, 50.217, -154.446]
      },
      {
        "name": "Light",
        "type": "DIRECTION",
        "intensity": 0.840,
        "direction": [-25.015, 9.024, -14.217]
      }
    ],
    "shapes": [
      {
        "type": "SPHERE",
        "name": "Check",
        "radius": 4.000,
        "transform": {
          "position": [0.000, 0.000, 0.000],
          "direction": [0.000, 1.000, 0.000]
        },
        "material": {
          "color": "FFFFFF",
          "specular": 0.100,
          "reflective": 0.000,
          "transparency": 0.000
        },
        "texture": {
          "name": "Checker"
        },
        "normal map": {
          "name": "ground"
        },
        "sections": {
          "style": "SIMPLE",
          "elements": [
            {
              "on": true,
              "type": "SPHERE",
              "position": [0.000, 0.000, 0.000],
              "radius": 3.000
            }
          ]
        }
      },
      {
        "type": "PLANE",
        "name": "Floor",
        "transform": {
          "position": [3.000, 1.601, -95.292],
          "direction": [0.000, 0.994, 0.105]
        },
        "material": {
          "color": "F0F484",
          "specular": 0.050,
          "reflective": 0.235,
          "transparency": 0.000
        },
        "texture": {
          "name": "NO TEXTURES"
        },
        "normal map": {
          "name": "NO NORMALS"
        },
        "sections": {
          "style": "SIMPLE",
          "elements": [
            {
              "on": false,
              "type": "PLANE",
              "position": [3.000, 1.601, -95.292],
              "direction": [0.000, 1.000, 0.000]
            }
          ]
        }
      },
      {
        "type": "PLANE",
        "name": "Front_wall",
        "transform": {
          "position": [3.000, 10.348, 54.152],
          "direction": [-0.000, 0.500, -0.866]
        },
        "material": {
          "color": "7FF29D",
          "specular": 0.050,
          "reflective": 0.235,
          "transparency": 0.000
        },
        "texture": {
          "name": "NO TEXTURES"
        },
        "normal map": {
          "name": "NO NORMALS"
        },
        "sections": {
          "style": "SIMPLE",
          "elements": [
            {
              "on": false,
              "type": "PLANE",
              "position": [3.000, 10.348, 54.152],
              "direction": [0.000, 1.000, 0.000]
            }
          ]
        }
      },
      {
        "type": "SPHERE",
        "name": "Check",
        "radius": 4.000,
        "transform": {
          "position": [10.500, 16.202, -109.846],
          "direction": [0.000, 1.000, 0.000]
        },
        "material": {
          "color": "FFFFFF",
          "specular": 0.100,
          "reflective": 0.000,
          "transparency": 0.000
        },
        "texture": {
          "name": "Checker"
        },
        "normal map": {
          "name": "ground"
        },
        "sections": {
          "style": "SIMPLE",
          "elements": [
            {
              "on": true,
              "type": "SPHERE",
              "position": [10.500, 16.202, -109.846],
              "radius": 3.000
            }
          ]
        }
      },
      {
        "type": "SPHERE",
        "name": "Check",
        "radius": 4.000,
        "transform": {
          "position": [-20.836, 26.917, -140.334],
          "direction": [0.000, 1.000, 0.000]
        },
        "material": {
          "color": "FFFFFF",
          "specular": 0.100,
          "reflective": 0.000,
          "transparency": 0.000
        },
        "texture": {
          "name": "Checker"
        },
        "normal map": {
          "name": "ground"
        },
        "sections": {
          "style": "SIMPLE",
          "elements": [
            {
              "on": true,
              "type": "SPHERE",
              "position": [-20.836, 26.917, -140.334],
              "radius": 3.000
            }
          ]
        }
      },
      {
        "type": "SPHERE",
        "name": "Check",
        "radius": 4.000,
        "transform": {
          "position": [4.034, 23.879, -154.548],
          "direction": [0.000, 1.000, 0.000]
        },
        "material": {
          "color": "FFFFFF",
          "specular": 0.100,
          "reflective": 0.000,
          "transparency": 0.000
        },
        "texture": {
          "name": "Checker"
        },
        "normal map": {
          "name": "ground"
        },
        "sections": {
          "style": "SIMPLE",
          "elements": [
            {
              "on": true,
              "type": "SPHERE",
              "position": [4.034, 23.879, -154.548],
              "radius": 3.000
            }
          ]
        }
      },
      {
        "type": "SPHERE",
        "name": "Check",
        "radius": 4.000,
        "transform": {
          "position": [11.893, 47.020, -157.611],
          "direction": [0.000, 1.000, 0.000]
        },
        "material": {
          "color": "FFFFFF",
          "specular": 0.100,
          "reflective": 0.000,
          "transparency": 0.000
        },
        "texture": {
          "name": "Checker"
        },
        "normal map": {
          "name": "ground"
        },
        "sections": {
          "style": "SIMPLE",
          "elements": [
            {
              "on": true,
              "type": "SPHERE",
              "position": [11.893, 47.020, -157.611],
              "radius": 3.000
            }
          ]
        }
      },
      {
        "type": "SPHERE",
        "name": "Check",
        "radius": 4.000,
        "transform": {
          "position": [-1.928, 26.991, -99.709],
          "direction": [0.000, 1.000, 0.000]
        },
        "material": {
          "color": "FFFFFF",
          "specular": 0.100,
          "reflective": 0.000,
          "transparency": 0.000
        },
        "texture": {
          "name": "Checker"
        },
        "normal map": {
          "name": "ground"
        },
        "sections": {
          "style": "SIMPLE",
          "elements": [
            {
              "on": true,
              "type": "SPHERE",
              "position": [-1.928, 26.991, -99.709],
              "radius": 3.000
            }
          ]
        }
      },
      {
        "type": "SPHERE",
        "name": "Check",
        "radius": 4.000,
        "transform": {
          "position": [27.512, 40.144, -175.025],
          "direction": [0.000, 1.000, 0.000]
        },
        "material": {
          "color": "FFFFFF",
          "specular": 0.100,
          "reflective": 0.000,
          "transparency": 0.000
        },
        "texture": {
          "name": "Checker"
        },
        "normal map": {
          "name": "ground"
        },
        "sections": {
          "style": "SIMPLE",
          "elements": [
            {
              "on": true,
              "type": "SPHERE",
              "position": [27.512, 40.144, -175.025],
              "radius": 3.000
            }
          ]
        }
      },
      {
        "type": "SPHERE",
        "name": "Check",
        "radius": 4.000,
        "transform": {
          "position": [33.360, 52.170, -177.820],
          "direction": [0.000, 1.000, 0.000]
        },
        "material": {
          "color": "FFFFFF",
          "specular": 0.100,
          "reflective": 0.000,
          "transparency": 0.000
        },
        "texture": {
          "name": "Checker"
        },
        "normal map": {
          "name": "ground"
        },
        "sections": {
          "style": "SIMPLE",
          "elements": [
            {
              "on": true,
              "type": "SPHERE",
              "position": [33.360, 52.170, -177.820],
              "radius": 3.000
            }
          ]
        }
      },
      {
        "type": "CONE",
        "name": "Cone",
        "angle": 30.009,
        "transform": {
          "position": [-6.661, 32.043, -112.421],
          "direction": [0.000, 0.951, 0.309]
        },
        "material": {
          "color": "84EDF4",
          "specular": 0.050,
          "reflective": 0.235,
          "transparency": 0.000
        },
        "texture": {
          "name": "NO TEXTURES"
        },
        "normal map": {
          "name": "NO NORMALS"
        },
        "sections": {
          "style": "SIMPLE",
          "elements": [
            {
              "on": false,
              "type": "PLANE",
              "position": [-6.661, 32.043, -112.421],
              "direction": [0.000, 1.000, 0.000]
            }
          ]
        }
      },
      {
        "type": "CONE",
        "name": "Cone",
        "angle": 30.009,
        "transform": {
          "position": [54.643, 34.193, -110.191],
          "direction": [0.000, 0.951, 0.309]
        },
        "material": {
          "color": "84E0F4",
          "specular": 0.050,
          "reflective": 0.235,
          "transparency": 0.000
        },
        "texture": {
          "name": "NO TEXTURES"
        },
        "normal map": {
          "name": "NO NORMALS"
        },
        "sections": {
          "style": "SIMPLE",
          "elements": [
            {
              "on": false,
              "type": "PLANE",
              "position": [54.643, 34.193, -110.191],
              "direction": [0.000, 1.000, 0.000]
            }
          ]
        }
      },
      {
        "type": "PLANE",
        "name": "Roof",
        "transform": {
          "position": [32.865, 105.796, -363.094],
          "direction": [0.000, 0.994, 0.105]
        },
        "material": {
          "color": "F484D5",
          "specular": 0.050,
          "reflective": 0.235,
          "transparency": 0.000
        },
        "texture": {
          "name": "NO TEXTURES"
        },
        "normal map": {
          "name": "NO NORMALS"
        },
        "sections": {
          "style": "SIMPLE",
          "elements": [
            {
              "on": false,
              "type": "PLANE",
              "position": [32.865, 105.796, -363.094],
              "direction": [0.000, 1.000, 0.000]
            }
          ]
        }
      },
      {
        "type": "PLANE",
        "name": "Back_wall",
        "transform": {
          "position": [60.550, 72.596, -282.810],
          "direction": [-0.000, 0.500, -0.866]
        },
        "material": {
          "color": "AE84F4",
          "specular": 0.050,
          "reflective": 0.235,
          "transparency": 0.000
        },
        "texture": {
          "name": "NO TEXTURES"
        },
        "normal map": {
          "name": "NO NORMALS"
        },
        "sections": {
          "style": "SIMPLE",
          "elements": [
            {
              "on": false,
              "type": "PLANE",
              "position": [60.550, 72.596, -282.810],
              "direction": [0.000, 1.000, 0.000]
            }
          ]
        }
      },
      {
        "type": "SPHERE",
        "name": "Shape",
        "radius": 0.500,
        "transform": {
          "position": [-1.909, 45.309, -155.744],
          "direction": [0.015, 0.976, 0.217]
        },
        "material": {
          "color": "84E0F4",
          "specular": 0.050,
          "reflective": 0.235,
          "transparency": 0.000
        },
        "texture": {
          "name": "NO TEXTURES"
        },
        "normal map": {
          "name": "NO NORMALS"
        },
        "sections": {
          "style": "SIMPLE",
          "elements": [
            {
              "on": false,
              "type": "PLANE",
              "position": [-1.909, 45.309, -155.744],
              "direction": [0.000, 1.000, 0.000]
            }
          ]
        }
      }
    ],
    "textures": [
      {
        "name": "norm",
        "path": "Wood.ppm"
      },
      {
        "name": "360",
        "path": "marble.ppm"
      },
      {
        "name": "Coffin",
        "path": "4.ppm"
      },
      {
        "name": "Dan",
        "path": "dan.ppm"
      },
      {
        "name": "Earth",
        "path": "earth.ppm"
      }
    ],
    "normal maps": [
      {
        "name": "ground",
        "path": "Wood_n.ppm"
      },
      {
        "name": "Wood",
        "path": "wow.ppm"
      },
      {
        "name": "Wood2",
        "path": "wow.ppm"
      },
      {
        "name": "Wood3",
        "path": "wow.ppm"
      },
      {
        "name": "Wood4",
        "path": "wow.ppm"
      }
    ]
  }
}